steam_grabber/__init__.py
steam_grabber/steam_grabber.py
steam_grabber-0.1.dist-info/METADATA
steam_grabber-0.1.dist-info/WHEEL
steam_grabber-0.1.dist-info/top_level.txt
steam_grabber-0.1.dist-info/RECORD
