Metadata-Version: 2.1
Name: steam-grabber
Version: 0.1
Summary: Async lib to grab a lot of useful info about an account. 2FA must be turned off. Supports proxy.
Author: Y0natari
Author-email: nickxon015@gmail.com
License: MIT
Requires-Dist: aiohttp
Requires-Dist: beautifulsoup4
Requires-Dist: rsa
Requires-Dist: yarl
